collider_check/__init__.py
collider_check/collider_check.py
collider_check/utils.py
collider_check-0.3.0.dist-info/LICENSE
collider_check-0.3.0.dist-info/METADATA
collider_check-0.3.0.dist-info/WHEEL
collider_check-0.3.0.dist-info/top_level.txt
collider_check-0.3.0.dist-info/RECORD
