Metadata-Version: 2.1
Name: collider-check
Version: 0.3.0
Summary: A small package that provides functions to check the observables in a collider, using a collider built with Xsuite.
Author-email: Colas Droin <colas.noe.droin@cern.ch>
License: MIT License
Project-URL: Homepage, https://github.com/ColasDroin/collider_check
Keywords: xsuite,accelerator,collider
Classifier: License :: OSI Approved :: MIT License
Classifier: Programming Language :: Python
Classifier: Programming Language :: Python :: 3
Requires-Python: <3.13,>=3.10
License-File: LICENSE
Requires-Dist: matplotlib >=3.9.2
Requires-Dist: numpy >=2.1.3
Requires-Dist: pandas >=2.2.3
Requires-Dist: pyyaml >=6.0.2
Requires-Dist: scipy >=1.14.1
Requires-Dist: xsuite >=0.19.2
